MANIFEST.in
README.md
requirements.txt
setup.py
futuquant/VERSION.txt
futuquant/__init__.py
futuquant.egg-info/PKG-INFO
futuquant.egg-info/SOURCES.txt
futuquant.egg-info/dependency_links.txt
futuquant.egg-info/requires.txt
futuquant.egg-info/top_level.txt
futuquant/common/__init__.py
futuquant/common/callback_executor.py
futuquant/common/conn_mng.py
futuquant/common/constant.py
futuquant/common/err.py
futuquant/common/ft_logger.py
futuquant/common/handler_context.py
futuquant/common/network_manager.py
futuquant/common/open_context_base.py
futuquant/common/pbjson.py
futuquant/common/sync_network_manager.py
futuquant/common/sys_config.py
futuquant/common/utils.py
futuquant/common/event/__init__.py
futuquant/common/event/eventEngine.py
futuquant/common/event/eventType.py
futuquant/common/pb/Common_pb2.py
futuquant/common/pb/GetGlobalState_pb2.py
futuquant/common/pb/InitConnect_pb2.py
futuquant/common/pb/KeepAlive_pb2.py
futuquant/common/pb/Notify_pb2.py
futuquant/common/pb/Qot_Common_pb2.py
futuquant/common/pb/Qot_GetBasicQot_pb2.py
futuquant/common/pb/Qot_GetBroker_pb2.py
futuquant/common/pb/Qot_GetHistoryKLPoints_pb2.py
futuquant/common/pb/Qot_GetHistoryKL_pb2.py
futuquant/common/pb/Qot_GetHoldingChangeList_pb2.py
futuquant/common/pb/Qot_GetKL_pb2.py
futuquant/common/pb/Qot_GetOptionChain_pb2.py
futuquant/common/pb/Qot_GetOrderBook_pb2.py
futuquant/common/pb/Qot_GetOrderDetail_pb2.py
futuquant/common/pb/Qot_GetOwnerPlate_pb2.py
futuquant/common/pb/Qot_GetPlateSecurity_pb2.py
futuquant/common/pb/Qot_GetPlateSet_pb2.py
futuquant/common/pb/Qot_GetRT_pb2.py
futuquant/common/pb/Qot_GetReference_pb2.py
futuquant/common/pb/Qot_GetRehab_pb2.py
futuquant/common/pb/Qot_GetSecuritySnapshot_pb2.py
futuquant/common/pb/Qot_GetStaticInfo_pb2.py
futuquant/common/pb/Qot_GetSubInfo_pb2.py
futuquant/common/pb/Qot_GetSuspend_pb2.py
futuquant/common/pb/Qot_GetTicker_pb2.py
futuquant/common/pb/Qot_GetTradeDate_pb2.py
futuquant/common/pb/Qot_RegQotPush_pb2.py
futuquant/common/pb/Qot_RequestHistoryKL_pb2.py
futuquant/common/pb/Qot_Sub_pb2.py
futuquant/common/pb/Qot_UpdateBasicQot_pb2.py
futuquant/common/pb/Qot_UpdateBroker_pb2.py
