Metadata-Version: 1.0
Name: futuquant
Version: 3.5.1
Summary: Futu Quantitative Trading API
Home-page: https://github.com/FutunnOpen/futuquant
Author: Futu, Inc.
Author-email: ftdev@futunn.com
License: Apache License 2.0
Keywords: Futu HK/US Stock Quant Trading API
Platform: UNKNOWN
